pypi_poetry_template/README.md
pypi_poetry_template/__init__.py
pypi_poetry_template/__main__.py
pypi_poetry_template/data/.gitkeep
pypi_poetry_template/gui/__init__.py
pypi_poetry_template/gui/main.py
pypi_poetry_template/utils/__init__.py
pypi_poetry_template-0.1.4.dist-info/LICENSE
pypi_poetry_template-0.1.4.dist-info/METADATA
pypi_poetry_template-0.1.4.dist-info/WHEEL
pypi_poetry_template-0.1.4.dist-info/RECORD
