Metadata-Version: 2.1
Name: pypi_poetry_template
Version: 0.1.4
Summary: a template for build python package to upload pypi repository bu using poetry
License: MIT
Keywords: packaging,poetry,template
Author: lgf4591
Author-email: lgf4591@outlook.com
Requires-Python: >=3.9,<4.0
Classifier: License :: OSI Approved :: MIT License
Classifier: Programming Language :: Python :: 3
Classifier: Programming Language :: Python :: 3.9
Classifier: Programming Language :: Python :: 3.10
Classifier: Programming Language :: Python :: 3.11
Classifier: Topic :: Software Development :: Build Tools
Classifier: Topic :: Software Development :: Libraries :: Python Modules
Requires-Dist: python-dotenv (>=1.0.0,<2.0.0)
Project-URL: Bug Tracker, https://github.com/lgf4591/pypi_poetry_templat/issues
Project-URL: documentation, https://github.com/lgf4591/pypi_poetry_template/blob/main/README.md
Project-URL: homepage, https://github.com/lgf4591/pypi_poetry_template
Project-URL: repository, https://github.com/lgf4591/pypi_poetry_template
